TSEnsemble/__init__.py
TSEnsemble/arima.py
TSEnsemble/ensemble.py
TSEnsemble/nn.py
TSEnsemble/utils.py
TSEnsemble-0.1.3.dist-info/LICENSE.txt
TSEnsemble-0.1.3.dist-info/METADATA
TSEnsemble-0.1.3.dist-info/WHEEL
TSEnsemble-0.1.3.dist-info/top_level.txt
TSEnsemble-0.1.3.dist-info/RECORD
